[
  {
    "event": "start",
    "timestamp": "2025-12-14T23:09:35.511479+00:00",
    "solar": {
      "sfi": "119",
      "k": " 1",
      "a": " 8",
      "geomagfield": "VR QUIET"
    }
  },
  {
    "event": "use",
    "antenna": "80ef1",
    "timestamp": "2025-12-14T23:15:08.268636+00:00",
    "description": "80m efhw, 49:1 balun systems unun at 5'; vertical segment to 30' high, continuing 42' due wsw then 60' due now dropping 15'"
  },
  {
    "event": "use",
    "antenna": "ryb",
    "timestamp": "2025-12-14T23:20:39.386992+00:00",
    "description": "Rybakov 25ft telescopic whip along back fence"
  },
  {
    "event": "use",
    "antenna": "80ef1",
    "timestamp": "2025-12-14T23:26:18.795034+00:00",
    "description": "80m efhw, 49:1 balun systems unun at 5'; vertical segment to 30' high, continuing 42' due wsw then 60' due now dropping 15'"
  },
  {
    "event": "use",
    "antenna": "ryb",
    "timestamp": "2025-12-14T23:30:58.334540+00:00",
    "description": "Rybakov 25ft telescopic whip along back fence"
  },
  {
    "event": "use",
    "antenna": "80ef1",
    "timestamp": "2025-12-14T23:36:19.559586+00:00",
    "description": "80m efhw, 49:1 balun systems unun at 5'; vertical segment to 30' high, continuing 42' due wsw then 60' due now dropping 15'"
  },
  {
    "event": "use",
    "antenna": "ryb",
    "timestamp": "2025-12-14T23:41:10.146610+00:00",
    "description": "Rybakov 25ft telescopic whip along back fence"
  },
  {
    "event": "stop",
    "timestamp": "2025-12-14T23:47:15.570294+00:00"
  }
]
